plt/__init__.py
plt_wrapper-0.0.2.dist-info/LICENSE
plt_wrapper-0.0.2.dist-info/METADATA
plt_wrapper-0.0.2.dist-info/WHEEL
plt_wrapper-0.0.2.dist-info/top_level.txt
plt_wrapper-0.0.2.dist-info/zip-safe
plt_wrapper-0.0.2.dist-info/RECORD
