Metadata-Version: 2.1
Name: plt-wrapper
Version: 0.0.2
Summary: A matplotib.pyplot wrapper for gpu arrays (cupy, pytorch, etc.) without any of the .get / .detach / .cpu abracadabra
Home-page: https://github.com/AleixBP/plt
Author: Aleix BOQUET-PUJADAS
License: MIT
Project-URL: Bug Tracker, https://github.com/AleixBP/plt/issues
Classifier: Development Status :: 4 - Beta
Classifier: Programming Language :: Python :: 3
Classifier: License :: OSI Approved :: MIT License
Classifier: Operating System :: OS Independent
Requires-Python: >=3.6
License-File: LICENSE
